maji_passport/README.rst
maji_passport/__init__.py
maji_passport/admin.py
maji_passport/apps.py
maji_passport/hooks.py
maji_passport/models.py
maji_passport/urls.py
maji_passport/utils.py
maji_passport/authentication/__init__.py
maji_passport/authentication/backend.py
maji_passport/management/__init__.py
maji_passport/management/commands/__init__.py
maji_passport/management/commands/kafka_consumer.py
maji_passport/management/commands/kafka_producer_test.py
maji_passport/management/commands/passport_check_random_users.py
maji_passport/management/commands/passport_users_delete_duplicate.py
maji_passport/management/commands/to_lowercase.py
maji_passport/migrations/0001_initial.py
maji_passport/migrations/0002_auto_20240418_1355.py
maji_passport/migrations/0003_accesstoken_passport_ac_token_cccee9_hash.py
maji_passport/migrations/0004_alter_accesstoken_passport_user.py
maji_passport/migrations/0005_auto_20240521_1047.py
maji_passport/migrations/0006_auto_20240521_1118.py
maji_passport/migrations/0007_auto_20240522_1304.py
maji_passport/migrations/0008_alter_passportuser_argo_user.py
maji_passport/migrations/0009_auto_20240603_1400.py
maji_passport/migrations/0010_alter_passportuser_social_networks.py
maji_passport/migrations/0011_auto_20240710_1916.py
maji_passport/migrations/0012_auto_20240722_0939.py
maji_passport/migrations/0013_alter_passportuser_passport_uuid.py
maji_passport/migrations/__init__.py
maji_passport/serializers/__init__.py
maji_passport/serializers/exchange.py
maji_passport/serializers/kafka.py
maji_passport/serializers/passport.py
maji_passport/services/__init__.py
maji_passport/services/auth.py
maji_passport/services/exchange.py
maji_passport/services/kafka.py
maji_passport/services/passport.py
maji_passport/services/passport_migrate.py
maji_passport/services/proxy.py
maji_passport/tests/__init__.py
maji_passport/tests/test_exchange.py
maji_passport/tests/test_kafka.py
maji_passport/views/__init__.py
maji_passport/views/exchange.py
maji_passport-1.0.10.dist-info/METADATA
maji_passport-1.0.10.dist-info/WHEEL
maji_passport-1.0.10.dist-info/licenses/LICENSE
maji_passport-1.0.10.dist-info/RECORD
