Metadata-Version: 2.4
Name: maji_passport
Version: 1.0.10
Summary: Maji Passport With custom authorisation
Project-URL: Homepage, https://gitlab.com/argo-media/argo-media-backend-ecosystem/maji-passport-library
Project-URL: Issues, https://gitlab.com/argo-media/argo-media-backend-ecosystem/maji-passport-library/issues
Author-email: Viktor Ivanov <viktorteodorihivanov@gmail.com>
License-File: LICENSE
Classifier: License :: OSI Approved :: MIT License
Classifier: Operating System :: OS Independent
Classifier: Programming Language :: Python :: 3
Requires-Python: >=3.9
Requires-Dist: confluent-kafka>=2.3
Requires-Dist: cryptography>=44
Requires-Dist: django-countries-plus>=2.2
Requires-Dist: django>=3.2
Requires-Dist: djangorestframework-simplejwt>=5.3
Requires-Dist: djangorestframework>=3.14
Requires-Dist: drf-yasg[validation]>=1.21
Requires-Dist: httpx>=0.27
Requires-Dist: loguru>=0.7
Requires-Dist: pillow>=10
Requires-Dist: pyjwt<3,>=2.10
Requires-Dist: sentry-sdk>=1.40
